{
  "research_projects": [
    {
      "id": "",
      "title": "",
      "status": "",              // "berjalan" | "selesai"
      "progress": 0,             // Wajib jika status = "berjalan"
      "category": "",            // Contoh: "pertanian", "biologi", "senjata", "energi"
      "date": ""
    }
  ],
  "technologies": [
    {
      "id": "",
      "name": "",
      "unlocked_by": "",         // ID riset yang membuka teknologi ini
      "status": "",              // "prototipe" | "aktif"
      "progress": 0              // Wajib jika status = "prototipe"
    }
  ]
}
